{
    "type": "FeatureCollection",
    "features": [
        {
    "type": "Feature",
    "properties": {
        "name": "Cutlery Works",
        "description": "A street food venue with a variety of global cuisines.",
        "timeCreated": 1676647678299
    },
    "geometry": {
        "type": "Point",
        "coordinates": [
            -1.478182899086022,
            53.392972738215775
        ]
    }
}
    ]
}