[
    {
        "type": "Feature",
        "properties": {
            "name": "Cutlery Works",
            "description": "A street food venue with a variety of global cuisines.",
            "type": "1",
            "timeCreated": 1676647678299
        },
        "geometry": {
            "type": "Point",
            "coordinates": [
                -1.478182899086022,
                53.392972738215775
            ]
        }
    },
    {
        "type": "Feature",
        "properties": {
            "name": "Best Burrito In Sheffield",
            "description": "the best burrito place in sheffield, has won many awards.",
            "type": "1",
            "timeCreated": 1676667537235
        },
        "geometry": {
            "type": "Point",
            "coordinates": [
                -1.4688229568619136,
                53.37654342555504
            ]
        }
    },
    {
        "type": "Feature",
        "properties": {
            "name": "Hot dog pop up",
            "description": "Hot dog and burger pop up van",
            "timeCreated": 1678894379006,
            "type": "1"
        },
        "geometry": {
            "type": "Point",
            "coordinates": [
                -0.11920195678013101,
                51.50947128830907
            ]
        }
    }
]
